model_mp_io/__init__.py
model_mp_io/classification_output.py
model_mp_io/detections_output.py
model_mp_io/image_reader.py
model_mp_io/image_writer.py
model_mp_io/io_windows.py
model_mp_io/segmentation_output.py
model_mp_io/txt_reader.py
model_mp_io-0.1.4.dist-info/LICENSE
model_mp_io-0.1.4.dist-info/METADATA
model_mp_io-0.1.4.dist-info/WHEEL
model_mp_io-0.1.4.dist-info/top_level.txt
model_mp_io-0.1.4.dist-info/RECORD
