Metadata-Version: 2.1
Name: model-mp-io
Version: 0.1.4
Summary: I/O utilities library for Mind+ model training tool
Home-page: https://github.com/UNIHIKER/model-pypi-lib
Author: unihiker Team
Author-email: unihiker Team <unihiker@dfrobot.com>
License: MIT License
Project-URL: Homepage, https://github.com/UNIHIKER/model-pypi-lib
Project-URL: Bug Tracker, https://github.com/UNIHIKER/model-pypi-lib/issues
Classifier: Programming Language :: Python :: 3
Classifier: License :: OSI Approved :: MIT License
Classifier: Operating System :: OS Independent
Classifier: Intended Audience :: Education
Classifier: Intended Audience :: Developers
Classifier: Topic :: Software Development :: Libraries :: Python Modules
Classifier: Topic :: Scientific/Engineering :: Artificial Intelligence
Classifier: Topic :: Education
Classifier: Topic :: Multimedia :: Graphics
Requires-Python: >=3.7
License-File: LICENSE
Requires-Dist: numpy>=1.19.0
Requires-Dist: opencv-python>=4.5.0
Requires-Dist: pillow>=8.0.0
Requires-Dist: matplotlib>=3.3.0
